{
	"name": "Rosters",
	"properties": {
		"activities": [
			{
				"name": "Organizations",
				"type": "Lookup",
				"dependsOn": [],
				"policy": {
					"timeout": "7.00:00:00",
					"retry": 0,
					"retryIntervalInSeconds": 30,
					"secureOutput": false,
					"secureInput": false
				},
				"userProperties": [],
				"typeProperties": {
					"source": {
						"type": "AzureSqlSource",
						"sqlReaderQuery": "SELECT organizationId\nFROM dbo.Definitiv_Organizations",
						"queryTimeout": "02:00:00",
						"partitionOption": "None"
					},
					"dataset": {
						"referenceName": "ds_SQL",
						"type": "DatasetReference",
						"parameters": {
							"param_SchemaName": "dbo",
							"param_TableName": "Definitiv_Organizations"
						}
					},
					"firstRowOnly": false
				}
			},
			{
				"name": "Organization",
				"type": "ForEach",
				"dependsOn": [
					{
						"activity": "Organizations",
						"dependencyConditions": [
							"Succeeded"
						]
					}
				],
				"userProperties": [],
				"typeProperties": {
					"items": {
						"value": "@activity('Organizations').output.value",
						"type": "Expression"
					},
					"activities": [
						{
							"name": "ApiToJson",
							"type": "Copy",
							"dependsOn": [],
							"policy": {
								"timeout": "0.03:00:00",
								"retry": 3,
								"retryIntervalInSeconds": 30,
								"secureOutput": false,
								"secureInput": false
							},
							"userProperties": [],
							"typeProperties": {
								"source": {
									"type": "RestSource",
									"additionalColumns": [
										{
											"name": "Org.OrganizationId",
											"value": {
												"value": "@item().organizationId",
												"type": "Expression"
											}
										}
									],
									"httpRequestTimeout": {
										"value": "@{pipeline().globalParameters.global_REST_RequestTimeoutDuration_30min}",
										"type": "Expression"
									},
									"requestInterval": "00.00:00:00.010",
									"requestMethod": "GET",
									"paginationRules": {
										"supportRFC5988": "true"
									}
								},
								"sink": {
									"type": "JsonSink",
									"storeSettings": {
										"type": "AzureBlobFSWriteSettings"
									},
									"formatSettings": {
										"type": "JsonWriteSettings"
									}
								},
								"enableStaging": false
							},
							"inputs": [
								{
									"referenceName": "ds_rest_definitiv",
									"type": "DatasetReference",
									"parameters": {
										"sourceRelativeUrl": {
											"value": "@concat(\n'/api/company/', \nitem().organizationId,\n'/reporting/rostering-v3',\n'?FromDate=',\nformatDateTime(convertFromUtc(addDays(utcNow(),-28), 'AUS Eastern Standard Time'), 'yyyy-MM-dd'),\n'&ToDate=',\nformatDateTime(convertFromUtc(addDays(utcNow(),28), 'AUS Eastern Standard Time'), 'yyyy-MM-dd')\n)",
											"type": "Expression"
										}
									}
								}
							],
							"outputs": [
								{
									"referenceName": "Rosters_ds",
									"type": "DatasetReference",
									"parameters": {
										"ds_PipelineTriggerTime": {
											"value": "@pipeline().TriggerTime",
											"type": "Expression"
										},
										"ds_PipelineRunId": {
											"value": "@pipeline().RunId",
											"type": "Expression"
										},
										"ds_FileSystem": {
											"value": "@pipeline().globalParameters.global_adls2_FileSystem",
											"type": "Expression"
										},
										"ds_Directory": {
											"value": "@pipeline().globalParameters.global_adls2_OutputDirectory_Json",
											"type": "Expression"
										},
										"ds_PipelineName": {
											"value": "@pipeline().Pipeline",
											"type": "Expression"
										}
									}
								}
							]
						}
					]
				}
			},
			{
				"name": "DefinitivRosters",
				"type": "ExecuteDataFlow",
				"dependsOn": [
					{
						"activity": "Organization",
						"dependencyConditions": [
							"Succeeded"
						]
					}
				],
				"policy": {
					"timeout": "0.03:00:00",
					"retry": 3,
					"retryIntervalInSeconds": 30,
					"secureOutput": false,
					"secureInput": false
				},
				"userProperties": [],
				"typeProperties": {
					"dataflow": {
						"referenceName": "Rosters_df",
						"type": "DataFlowReference",
						"datasetParameters": {
							"jsoninput": {
								"ds_PipelineTriggerTime": {
									"value": "@pipeline().TriggerTime",
									"type": "Expression"
								},
								"ds_PipelineRunId": {
									"value": "@pipeline().RunId",
									"type": "Expression"
								},
								"ds_FileSystem": {
									"value": "@pipeline().globalParameters.global_adls2_FileSystem",
									"type": "Expression"
								},
								"ds_Directory": {
									"value": "@pipeline().globalParameters.global_adls2_OutputDirectory_Json",
									"type": "Expression"
								},
								"ds_PipelineName": {
									"value": "@pipeline().Pipeline",
									"type": "Expression"
								}
							},
							"WriteToSQLDB": {
								"param_SchemaName": "dbo",
								"param_TableName": "Definitv_Rosters"
							}
						}
					},
					"compute": {
						"coreCount": 8,
						"computeType": "General"
					},
					"traceLevel": "Fine"
				}
			}
		],
		"parameters": {
			"param_SchemaName": {
				"type": "string",
				"defaultValue": "dbo"
			},
			"param_TableName": {
				"type": "string",
				"defaultValue": "Definitv_Rosters"
			}
		},
		"folder": {
			"name": "00_Definitiv Pipelines"
		},
		"annotations": []
	}
}